t625187/verilog_simulation/src/your_design.v
module pipelined_multiplier_3stage (
    input clk,
    input reset,
    input [7:0] a,
    input [7:0] b,
    output reg [15:0] product
);

    reg [7:0] a_reg1, b_reg1;
    reg [15:0] partial_result;
    reg [15:0] final_result;

    always @(posedge clk or posedge reset) begin
        if (reset) begin
            a_reg1        <= 8'd0;
            b_reg1        <= 8'd0;
            partial_result <= 16'd0;
            final_result  <= 16'd0;
            product       <= 16'd0;
        end else begin
            a_reg1 <= a;
            b_reg1 <= b;

            partial_result <= a_reg1 * b_reg1;

            final_result <= partial_result;
            product <= final_result;
        end
    end
endmodule

t625187/verilog_simulation/src/testbench.v
`timescale 1ns / 1ps

module tb_pipelined_multiplier_3stage;
    
    // Testbench Signals
    reg clk;
    reg reset;
    reg [7:0] a, b;
    wire [15:0] product;
    
    // Instantiate the DUT (Device Under Test)
    pipelined_multiplier_3stage uut (
        .clk(clk),
        .reset(reset),
        .a(a),
        .b(b),
        .product(product)
    );
    
    // Clock Generation (10 ns period -> 100 MHz)
    always #5 clk = ~clk;
    
    
initial begin
        $dumpfile("output/tb_pipelined_multiplier_3stage.vcd");
        $dumpvars(0, tb_pipelined_multiplier_3stage);
    end
    // Test Procedure
    initial begin
        // Initialize signals
        clk = 0;
        reset = 1;
        a = 0;
        b = 0;
        
        // Hold reset for a few clock cycles
        #10;
        reset = 0;
        
        // Apply test vectors
        #10; a = 8'd10; b = 8'd5;    // 10 * 5  = 50
        #10; a = 8'd3;  b = 8'd7;    // 3  * 7  = 21
        #10; a = 8'd15; b = 8'd15;   // 15 * 15 = 225
        #10; a = 8'd25; b = 8'd12;   // 25 * 12 = 300
        #10; a = 8'd8;  b = 8'd20;   // 8  * 20 = 160
        
        // Wait for pipeline to propagate results
        #50;
        
        // Finish simulation
        $finish;
    end
    
    // Monitor output
    initial begin
        $monitor("Time: %0t | a: %d, b: %d, product: %d", $time, a, b, product);
    end
    
endmodule

t625187/verilog_simulation/output/tb_pipelined_multiplier_3stage.vcd
$date
	Mon Mar 31 16:34:47 2025
$end
$version
	Icarus Verilog
$end
$timescale
	1ps
$end
$scope module tb_pipelined_multiplier_3stage $end
$var wire 16 ! product [15:0] $end
$var reg 8 " a [7:0] $end
$var reg 8 # b [7:0] $end
$var reg 1 $ clk $end
$var reg 1 % reset $end
$scope module uut $end
$var wire 8 & a [7:0] $end
$var wire 8 ' b [7:0] $end
$var wire 1 $ clk $end
$var wire 1 % reset $end
$var reg 8 ( a_reg1 [7:0] $end
$var reg 8 ) b_reg1 [7:0] $end
$var reg 16 * final_result [15:0] $end
$var reg 16 + partial_result [15:0] $end
$var reg 16 , product [15:0] $end
$upscope $end
$upscope $end
$enddefinitions $end
$comment Show the parameter values. $end
$dumpall
$end
#0
$dumpvars
b0 ,
b0 +
b0 *
b0 )
b0 (
b0 '
b0 &
1%
0$
b0 #
b0 "
b0 !
$end
#5000
1$
#10000
0$
0%
#15000
1$
#20000
0$
b101 #
b101 '
b1010 "
b1010 &
#25000
b101 )
b1010 (
1$
#30000
0$
b111 #
b111 '
b11 "
b11 &
#35000
b110010 +
b111 )
b11 (
1$
#40000
0$
b1111 #
b1111 '
b1111 "
b1111 &
#45000
b110010 *
b10101 +
b1111 )
b1111 (
1$
#50000
0$
b1100 #
b1100 '
b11001 "
b11001 &
#55000
b110010 !
b110010 ,
b10101 *
b11100001 +
b1100 )
b11001 (
1$
#60000
0$
b10100 #
b10100 '
b1000 "
b1000 &
#65000
b10101 !
b10101 ,
b11100001 *
b100101100 +
b10100 )
b1000 (
1$
#70000
0$
#75000
b11100001 !
b11100001 ,
b100101100 *
b10100000 +
1$
#80000
0$
#85000
b100101100 !
b100101100 ,
b10100000 *
1$
#90000
0$
#95000
b10100000 !
b10100000 ,
1$
