t625106/verilog_simulation/src/your_design.v
module dynamic_clock_gating (
    input wire clk,          // Main clock input
    input wire reset_n,      // Active-low reset
    input wire activity,     // Activity signal (1 = active, 0 = idle)
    output wire gated_clk     // Gated clock output
);

    reg enable;              // Clock enable register

    always @(posedge clk or negedge reset_n) begin
        if (!reset_n) begin
            enable <= 1'b0;
            
        end else begin
            // Update enable based on activity signal
            enable <= activity;       
        end
    end
assign gated_clk=(enable)?clk:0;
endmodule

t625106/verilog_simulation/src/testbench.v
`timescale 1ns/1ps

module tb_dynamic_clock_gating();
    // Inputs
    reg clk;
    reg reset_n;
    reg activity;
    
    // Outputs
    wire gated_clk;
    
    // Instantiate the Unit Under Test (UUT)
    dynamic_clock_gating uut (
        .clk(clk),
        .reset_n(reset_n),
        .activity(activity),
        .gated_clk(gated_clk)
    );
    
    // Clock generation
    initial begin
        clk = 0;
        forever #5 clk = ~clk; // 100MHz clock (10ns period)
    end
    
    // Main test sequence
    initial begin
        // Initialize inputs
        reset_n = 0;
        activity = 0;
        
        // System reset
        #20;
        reset_n = 1;
        
        // Test 1: Verify clock gating when inactive
        $display("[%0t] Test 1: Clock gating when inactive", $time);
        activity = 0;
        #50;
        if (gated_clk !== 0)
            $error("Clock not gated when inactive");
        
        // Test 2: Verify clock enable when active
        $display("[%0t] Test 2: Clock enable when active", $time);
        activity = 1;
        #50;
        if (gated_clk !== clk)
            $error("Clock not enabled when active");
        
        // Test 3: Verify dynamic switching
        $display("[%0t] Test 3: Dynamic switching", $time);
        repeat (5) begin
            activity = ~activity;
            #30;
            // Verify gated_clk follows activity with 1 clock delay
            if (activity && (gated_clk !== clk))
                $error("Clock not enabled when activity high");
            if (!activity && (gated_clk !== 0))
                $error("Clock not gated when activity low");
        end
        
        // Test 4: Verify reset behavior
        $display("[%0t] Test 4: Reset behavior", $time);
        reset_n = 0;
        activity = 1; // Try to keep clock enabled during reset
        #20;
        if (gated_clk !== 0)
            $error("Clock not gated during reset");
        
        // Release reset and verify
        reset_n = 1;
        #10;
        if (gated_clk !== 0)
            $error("Clock not properly initialized after reset");
        
        // Final check
        activity = 1;
        #20;
        if (gated_clk !== clk)
            $error("Final enable check failed");
        
        $display("[%0t] All tests completed successfully", $time);
        $finish;
    end
    
    // Monitoring
    always @(posedge clk) begin
        $display("[%0t] CLK: %b, Activity: %b, Gated_CLK: %b", 
                $time, clk, activity, gated_clk);
    end
    
    // Waveform dumping (for visualization tools)
    initial begin
        $dumpfile("output/dynamic_clock_gating.vcd");
        $dumpvars(0, tb_dynamic_clock_gating);
    end
endmodule

t625106/verilog_simulation/output/dynamic_clock_gating.vcd
$date
	Tue Apr  1 11:53:23 2025
$end
$version
	Icarus Verilog
$end
$timescale
	1ps
$end
$scope module tb_dynamic_clock_gating $end
$var wire 1 ! gated_clk $end
$var reg 1 " activity $end
$var reg 1 # clk $end
$var reg 1 $ reset_n $end
$scope module uut $end
$var wire 1 " activity $end
$var wire 1 # clk $end
$var wire 1 $ reset_n $end
$var wire 1 ! gated_clk $end
$var reg 1 % enable $end
$upscope $end
$upscope $end
$enddefinitions $end
$comment Show the parameter values. $end
$dumpall
$end
#0
$dumpvars
0%
0$
0#
0"
0!
$end
#5000
1#
#10000
0#
#15000
1#
#20000
0#
1$
#25000
1#
#30000
0#
#35000
1#
#40000
0#
#45000
1#
#50000
0#
#55000
1#
#60000
0#
#65000
1#
#70000
0#
1"
#75000
1!
1%
1#
#80000
0!
0#
#85000
1!
1#
#90000
0!
0#
#95000
1!
1#
#100000
0!
0#
#105000
1!
1#
#110000
0!
0#
#115000
1!
1#
#120000
0!
0#
0"
#125000
0%
0!
1#
#130000
0#
#135000
1#
#140000
0#
#145000
1#
#150000
0#
1"
#155000
1!
1%
1#
#160000
0!
0#
#165000
1!
1#
#170000
0!
0#
#175000
1!
1#
#180000
0!
0#
0"
#185000
0%
0!
1#
#190000
0#
#195000
1#
#200000
0#
#205000
1#
#210000
0#
1"
#215000
1!
1%
1#
#220000
0!
0#
#225000
1!
1#
#230000
0!
0#
#235000
1!
1#
#240000
0!
0#
0"
#245000
0%
0!
1#
#250000
0#
#255000
1#
#260000
0#
#265000
1#
#270000
0#
1"
0$
#275000
1#
#280000
0#
#285000
1#
#290000
0#
1$
#295000
1!
1%
1#
