verilog_simulation/your_design.sv
`timescale 1ns / 1ps

module ALU #(parameter WIDTH = 8) (
    input  logic [WIDTH-1:0] A, B,
    input  logic [2:0] ALU_Sel,
    output logic [WIDTH-1:0] ALU_Out,
    output logic Zero
);

always begin
        case (ALU_Sel)
            3'b000: ALU_Out = A + B;       // Addition
            3'b001: ALU_Out = A - B;       // Subtraction
            3'b010: ALU_Out = A & B;       // Bitwise AND
            3'b011: ALU_Out = A | B;       // Bitwise OR
            3'b100: ALU_Out = A ^ B;       // Bitwise XOR
            3'b101: ALU_Out = A << 1;      // Left Shift
            3'b110: ALU_Out = A >> 1;      // Right Shift
            3'b111: ALU_Out = (A < B) ? 1 : 0; // Less Than
            default: ALU_Out = 0;
        endcase
    end
    
    assign Zero = (ALU_Out == 0) ? 1 : 0; // Zero flag
    
endmodule

verilog_simulation/testbench.sv
`timescale 1ns / 1ps

module ALU_tb;
    // Parameter for ALU width
    parameter WIDTH = 8;
    
    // Testbench signals
    logic [WIDTH-1:0] A, B;
    logic [2:0] ALU_Sel;
    logic [WIDTH-1:0] ALU_Out;
    logic Zero;
    
    // Instantiate the ALU module
    ALU #(WIDTH) uut (
        .A(A),
        .B(B),
        .ALU_Sel(ALU_Sel),
        .ALU_Out(ALU_Out),
        .Zero(Zero)
    );
    
    // Test procedure
    initial begin
        // Apply test cases
        A = 8'h05; B = 8'h03; 
        ALU_Sel = 3'b000; #10; // Addition: 5 + 3 = 8
        
        ALU_Sel = 3'b001; #10; // Subtraction: 5 - 3 = 2
        
        ALU_Sel = 3'b010; #10; // AND: 5 & 3 = 00000001
        
        ALU_Sel = 3'b011; #10; // OR: 5 | 3 = 00000111
        
        ALU_Sel = 3'b100; #10; // XOR: 5 ^ 3 = 00000110
        
        ALU_Sel = 3'b101; #10; // Left Shift: 5 << 1 = 00001010
        
        ALU_Sel = 3'b110; #10; // Right Shift: 5 >> 1 = 00000010
        
        ALU_Sel = 3'b111; #10; // Less Than: (5 < 3) ? 1 : 0 = 0
        
        A = 8'h02; B = 8'h04; // Changing A & B
        ALU_Sel = 3'b111; #10; // Less Than: (2 < 4) ? 1 : 0 = 1
        
        A = 8'h00; B = 8'h00;
        ALU_Sel = 3'b000; #10; // Zero flag check (0 + 0 = 0)
        
        // Finish simulation
        $finish;
    end
    
    // Monitor output
    initial begin
        $monitor("Time=%0t | A=%h, B=%h, ALU_Sel=%b -> ALU_Out=%h, Zero=%b", 
                 $time, A, B, ALU_Sel, ALU_Out, Zero);
    end
    
    // Dump waveforms
    initial begin
        $dumpfile("ALU_tb.vcd");
        $dumpvars(0, ALU_tb);
    end
    
endmodule

t625052/verilog_simulation/output/ALU_tb.vcd
$date
	Mon Mar 31 11:55:22 2025
$end
$version
	Icarus Verilog
$end
$timescale
	1ps
$end
$scope module ALU_tb $end
$var wire 1 ! Zero $end
$var wire 8 " ALU_Out [7:0] $end
$var parameter 32 # WIDTH $end
$var reg 8 $ A [7:0] $end
$var reg 3 % ALU_Sel [2:0] $end
$var reg 8 & B [7:0] $end
$scope module uut $end
$var wire 8 ' A [7:0] $end
$var wire 3 ( ALU_Sel [2:0] $end
$var wire 8 ) B [7:0] $end
$var parameter 32 * WIDTH $end
$var reg 8 + ALU_Out [7:0] $end
$var reg 1 ! Zero $end
$upscope $end
$upscope $end
$enddefinitions $end
$comment Show the parameter values. $end
$dumpall
b1000 *
b1000 #
$end
#0
$dumpvars
b1000 +
b11 )
b0 (
b101 '
b11 &
b0 %
b101 $
b1000 "
0!
$end
#10000
b10 "
b10 +
b1 %
b1 (
#20000
b1 "
b1 +
b10 %
b10 (
#30000
b111 "
b111 +
b11 %
b11 (
#40000
b110 "
b110 +
b100 %
b100 (
#50000
b1010 "
b1010 +
b101 %
b101 (
#60000
b10 "
b10 +
b110 %
b110 (
#70000
1!
b0 "
b0 +
b111 %
b111 (
#80000
0!
b1 "
b1 +
b100 &
b100 )
b10 $
b10 '
#90000
1!
b0 "
b0 +
b0 %
b0 (
b0 &
b0 )
b0 $
b0 '
