t625027/verilog_simulation/src/your_design.v
module dual_port_sram #(
    parameter DATA_WIDTH = 32,
    parameter ADDR_WIDTH = 10,
    parameter MEM_DEPTH  = 1 << ADDR_WIDTH
)(
    input wire                  clk_a,
    input wire                  we_a,
    input wire [ADDR_WIDTH-1:0] addr_a,
    input wire [DATA_WIDTH-1:0] din_a,
    output reg [DATA_WIDTH-1:0] dout_a,

    input wire                  clk_b,
    input wire                  we_b,
    input wire [ADDR_WIDTH-1:0] addr_b,
    input wire [DATA_WIDTH-1:0] din_b,
    output reg [DATA_WIDTH-1:0] dout_b
);

    // Memory declaration
    reg [DATA_WIDTH-1:0] mem [0:MEM_DEPTH-1];

    // Port A
    always @(posedge clk_a) begin
        if (we_a)
            mem[addr_a] <= din_a;

        // Handle read-after-write coherency
        if (we_b && addr_b == addr_a && !we_a) begin
            // If Port B is writing to addr_a, and Port A is reading it
            dout_a <= din_b; // Forwarding
        end else begin
            dout_a <= mem[addr_a];
        end
    end

    // Port B
    always @(posedge clk_b) begin
        if (we_b)
            mem[addr_b] <= din_b;

        // Handle read-after-write coherency
        if (we_a && addr_a == addr_b && !we_b) begin
            dout_b <= din_a;
        end else begin
            dout_b <= mem[addr_b];
        end
    end

endmodule

t625027/verilog_simulation/src/testbench.v
`timescale 1ns/1ps

module dual_port_sram_tb;
    parameter DATA_WIDTH = 32;
    parameter ADDR_WIDTH = 10;
    parameter MEM_DEPTH  = 1 << ADDR_WIDTH;

    reg clk_a, clk_b;
    reg we_a, we_b;
    reg [ADDR_WIDTH-1:0] addr_a, addr_b;
    reg [DATA_WIDTH-1:0] din_a, din_b;
    wire [DATA_WIDTH-1:0] dout_a, dout_b;

    // Instantiate the dual-port SRAM module
    dual_port_sram #(
        .DATA_WIDTH(DATA_WIDTH),
        .ADDR_WIDTH(ADDR_WIDTH)
    ) uut (
        .clk_a(clk_a),
        .we_a(we_a),
        .addr_a(addr_a),
        .din_a(din_a),
        .dout_a(dout_a),
        .clk_b(clk_b),
        .we_b(we_b),
        .addr_b(addr_b),
        .din_b(din_b),
        .dout_b(dout_b)
    );

    // Clock generation
    always #5 clk_a = ~clk_a;
    always #7 clk_b = ~clk_b;

initial begin
        $dumpfile("output/dual_port_sram_tb.vcd");
        $dumpvars(0, dual_port_sram_tb);
    end
    initial begin
        // Initialize signals
        clk_a = 0; clk_b = 0;
        we_a = 0; we_b = 0;
        addr_a = 0; addr_b = 0;
        din_a = 0; din_b = 0;

        // Write to Port A
        #10;
        we_a = 1; addr_a = 10; din_a = 32'hA5A5A5A5;
        #10;
        we_a = 0;

        // Read from Port A
        #10;
        addr_a = 10;
        #10;
        $display("Read from Port A: %h", dout_a);

        // Write to Port B at the same address as Port A
        #10;
        we_b = 1; addr_b = 10; din_b = 32'h5A5A5A5A;
        #20;
        we_b = 0;

        // Read from Port B
        #20;
        addr_b = 10;
        #20;
        $display("Read from Port B: %h", dout_b);

        // Test read-after-write forwarding
        #20;
        we_a = 1; addr_a = 20; din_a = 32'hDEADBEEF;
        we_b = 1; addr_b = 20; din_b = 32'hFEEDFACE;
        #20;
        we_a = 0; we_b = 0;

        addr_a = 20;
        addr_b = 20;
        #10;
        $display("Read from Port A after write conflict: %h", dout_a);
        $display("Read from Port B after write conflict: %h", dout_b);

        // End simulation
        #20;
        $finish;
    end
endmodule

t625027/verilog_simulation/output/dual_port_sram_tb.vcd
$date
	Mon Mar 31 15:08:15 2025
$end
$version
	Icarus Verilog
$end
$timescale
	1ps
$end
$scope module dual_port_sram_tb $end
$var wire 32 ! dout_b [31:0] $end
$var wire 32 " dout_a [31:0] $end
$var parameter 32 # ADDR_WIDTH $end
$var parameter 32 $ DATA_WIDTH $end
$var parameter 42 % MEM_DEPTH $end
$var reg 10 & addr_a [9:0] $end
$var reg 10 ' addr_b [9:0] $end
$var reg 1 ( clk_a $end
$var reg 1 ) clk_b $end
$var reg 32 * din_a [31:0] $end
$var reg 32 + din_b [31:0] $end
$var reg 1 , we_a $end
$var reg 1 - we_b $end
$scope module uut $end
$var wire 10 . addr_a [9:0] $end
$var wire 10 / addr_b [9:0] $end
$var wire 1 ( clk_a $end
$var wire 1 ) clk_b $end
$var wire 32 0 din_a [31:0] $end
$var wire 32 1 din_b [31:0] $end
$var wire 1 , we_a $end
$var wire 1 - we_b $end
$var parameter 32 2 ADDR_WIDTH $end
$var parameter 32 3 DATA_WIDTH $end
$var parameter 42 4 MEM_DEPTH $end
$var reg 32 5 dout_a [31:0] $end
$var reg 32 6 dout_b [31:0] $end
$upscope $end
$upscope $end
$enddefinitions $end
$comment Show the parameter values. $end
$dumpall
b10000000000 4
b100000 3
b1010 2
b10000000000 %
b100000 $
b1010 #
$end
#0
$dumpvars
bx 6
bx 5
b0 1
b0 0
b0 /
b0 .
0-
0,
b0 +
b0 *
0)
0(
b0 '
b0 &
bx "
bx !
$end
#5000
1(
#7000
1)
#10000
0(
b10100101101001011010010110100101 *
b10100101101001011010010110100101 0
b1010 &
b1010 .
1,
#14000
0)
#15000
1(
#20000
0(
0,
#21000
1)
#25000
b10100101101001011010010110100101 "
b10100101101001011010010110100101 5
1(
#28000
0)
#30000
0(
#35000
1(
1)
#40000
0(
#42000
0)
#45000
1(
#49000
1)
#50000
0(
b1011010010110100101101001011010 +
b1011010010110100101101001011010 1
b1010 '
b1010 /
1-
#55000
b1011010010110100101101001011010 "
b1011010010110100101101001011010 5
1(
#56000
0)
#60000
0(
#63000
b10100101101001011010010110100101 !
b10100101101001011010010110100101 6
1)
#65000
1(
#70000
0(
0)
0-
#75000
1(
#77000
b1011010010110100101101001011010 !
b1011010010110100101101001011010 6
1)
#80000
0(
#84000
0)
#85000
1(
#90000
0(
#91000
1)
#95000
1(
#98000
0)
#100000
0(
#105000
1(
1)
#110000
0(
#112000
0)
#115000
1(
#119000
1)
#120000
0(
#125000
1(
#126000
0)
#130000
0(
b11111110111011011111101011001110 +
b11111110111011011111101011001110 1
b10100 '
b10100 /
1-
b11011110101011011011111011101111 *
b11011110101011011011111011101111 0
b10100 &
b10100 .
1,
#133000
bx !
bx 6
1)
#135000
b11111110111011011111101011001110 "
b11111110111011011111101011001110 5
1(
#140000
0(
0)
#145000
b11011110101011011011111011101111 "
b11011110101011011011111011101111 5
1(
#147000
b11011110101011011011111011101111 !
b11011110101011011011111011101111 6
1)
#150000
0(
0-
0,
#154000
0)
#155000
b11111110111011011111101011001110 "
b11111110111011011111101011001110 5
1(
#160000
0(
#161000
b11111110111011011111101011001110 !
b11111110111011011111101011001110 6
1)
