t625193/verilog_simulation/src/your_design.v
module acc_pipeline (
    input clk,
    input reset,
    input [15:0] vehicle_speed,
    input [15:0] lead_vehicle_speed,
    input [15:0] distance_to_lead,
    output reg [7:0] throttle_out,
    output reg [7:0] brake_out
);

    // Stage 1: Sensor Input Registers
    reg [15:0] s1_vehicle_speed, s1_lead_speed, s1_distance;

    // Stage 2: Relative Speed & Distance Evaluation
    reg signed [15:0] s2_rel_speed;
    reg [15:0] s2_distance;

    // Stage 3: Control Decision Logic
    reg s3_brake_cmd;
    reg s3_throttle_cmd;

    // Stage 4: Output Signal Generation
    always @(posedge clk or posedge reset) begin
        if (reset) begin
            // Reset all pipeline registers
            s1_vehicle_speed <= 0; s1_lead_speed <= 0; s1_distance <= 0;
            s2_rel_speed <= 0; s2_distance <= 0;
            s3_brake_cmd <= 0; s3_throttle_cmd <= 0;
            throttle_out <= 0; brake_out <= 0;
        end else begin
            // Stage 1: Sensor data latch
            s1_vehicle_speed <= vehicle_speed;
            s1_lead_speed <= lead_vehicle_speed;
            s1_distance <= distance_to_lead;

            // Stage 2: Relative speed calc
            s2_rel_speed <= $signed(s1_vehicle_speed) - $signed(s1_lead_speed);
            s2_distance <= s1_distance;

            // Stage 3: Predictive Control Logic
            if (s2_distance < 60 && s2_rel_speed > 10) begin
                s3_brake_cmd <= 1;
                s3_throttle_cmd <= 0;
            end else if (s2_distance > 110 && s2_rel_speed < -10) begin
                s3_brake_cmd <= 0;
                s3_throttle_cmd <= 1;
            end else begin
                s3_brake_cmd <= 0;
                s3_throttle_cmd <= 0;
            end

            // Stage 4: Actuator signal output
            if (s3_brake_cmd) begin
                brake_out <= 8'd255;
                throttle_out <= 8'd0;
            end else if (s3_throttle_cmd) begin
                throttle_out <= 8'd180;
                brake_out <= 8'd0;
            end else begin
                throttle_out <= 8'd100; // cruising value
                brake_out <= 8'd0;
            end
        end
    end
endmodule

t625193/verilog_simulation/src/testbench.v
`timescale 1ns / 1ps

module acc_pipeline_tb;

    reg clk;
    reg reset;
    reg [15:0] vehicle_speed;
    reg [15:0] lead_vehicle_speed;
    reg [15:0] distance_to_lead;
    wire [7:0] throttle_out;
    wire [7:0] brake_out;

    // Instantiate the ACC pipeline module
    acc_pipeline uut (
        .clk(clk),
        .reset(reset),
        .vehicle_speed(vehicle_speed),
        .lead_vehicle_speed(lead_vehicle_speed),
        .distance_to_lead(distance_to_lead),
        .throttle_out(throttle_out),
        .brake_out(brake_out)
    );

    // Clock generation
    always #5 clk = ~clk; // 10ns clock period

    initial begin
        // Initialize inputs
        clk = 0;
        reset = 1;
        vehicle_speed = 0;
        lead_vehicle_speed = 0;
        distance_to_lead = 0;
        
        // Apply reset
        #20;
        reset = 0;
        
        // Test Case 1: Normal cruising
        vehicle_speed = 60;
        lead_vehicle_speed = 60;
        distance_to_lead = 100;
        #50;
        
        // Test Case 2: Lead vehicle slows down, closer distance
        vehicle_speed = 60;
        lead_vehicle_speed = 50;
        distance_to_lead = 50;
        #50;
        
        // Test Case 3: Lead vehicle far away, need acceleration
        vehicle_speed = 50;
        lead_vehicle_speed = 70;
        distance_to_lead = 120;
        #50;
        
        // Test Case 4: Emergency braking required
        vehicle_speed = 80;
        lead_vehicle_speed = 50;
        distance_to_lead = 40;
        #50;

        // Test Case 5: Safe distance, no action needed
        vehicle_speed = 60;
        lead_vehicle_speed = 60;
        distance_to_lead = 90;
        #50;
        
        // Finish simulation
        $finish;
    end
initial begin
        $dumpfile("output/acc_pipeline_tb.vcd");
        $dumpvars(0, acc_pipeline_tb);
    end


endmodule

t625193/verilog_simulation/output/acc_pipeline_tb.vcd
$date
	Mon Mar 31 17:20:33 2025
$end
$version
	Icarus Verilog
$end
$timescale
	1ps
$end
$scope module acc_pipeline_tb $end
$var wire 8 ! throttle_out [7:0] $end
$var wire 8 " brake_out [7:0] $end
$var reg 1 # clk $end
$var reg 16 $ distance_to_lead [15:0] $end
$var reg 16 % lead_vehicle_speed [15:0] $end
$var reg 1 & reset $end
$var reg 16 ' vehicle_speed [15:0] $end
$scope module uut $end
$var wire 1 # clk $end
$var wire 16 ( distance_to_lead [15:0] $end
$var wire 16 ) lead_vehicle_speed [15:0] $end
$var wire 1 & reset $end
$var wire 16 * vehicle_speed [15:0] $end
$var reg 8 + brake_out [7:0] $end
$var reg 16 , s1_distance [15:0] $end
$var reg 16 - s1_lead_speed [15:0] $end
$var reg 16 . s1_vehicle_speed [15:0] $end
$var reg 16 / s2_distance [15:0] $end
$var reg 16 0 s2_rel_speed [15:0] $end
$var reg 1 1 s3_brake_cmd $end
$var reg 1 2 s3_throttle_cmd $end
$var reg 8 3 throttle_out [7:0] $end
$upscope $end
$upscope $end
$enddefinitions $end
$comment Show the parameter values. $end
$dumpall
$end
#0
$dumpvars
b0 3
02
01
b0 0
b0 /
b0 .
b0 -
b0 ,
b0 +
b0 *
b0 )
b0 (
b0 '
1&
b0 %
b0 $
0#
b0 "
b0 !
$end
#5000
1#
#10000
0#
#15000
1#
#20000
0#
b1100100 $
b1100100 (
b111100 %
b111100 )
b111100 '
b111100 *
0&
#25000
b1100100 !
b1100100 3
b1100100 ,
b111100 -
b111100 .
1#
#30000
0#
#35000
b1100100 /
1#
#40000
0#
#45000
1#
#50000
0#
#55000
1#
#60000
0#
#65000
1#
#70000
0#
b110010 $
b110010 (
b110010 %
b110010 )
#75000
b110010 ,
b110010 -
1#
#80000
0#
#85000
b110010 /
b1010 0
1#
#90000
0#
#95000
1#
#100000
0#
#105000
1#
#110000
0#
#115000
1#
#120000
0#
b1111000 $
b1111000 (
b1000110 %
b1000110 )
b110010 '
b110010 *
#125000
b1111000 ,
b1000110 -
b110010 .
1#
#130000
0#
#135000
b1111000 /
b1111111111101100 0
1#
#140000
0#
#145000
12
1#
#150000
0#
#155000
b10110100 !
b10110100 3
1#
#160000
0#
#165000
1#
#170000
0#
b101000 $
b101000 (
b110010 %
b110010 )
b1010000 '
b1010000 *
#175000
b101000 ,
b110010 -
b1010000 .
1#
#180000
0#
#185000
b101000 /
b11110 0
1#
#190000
0#
#195000
02
11
1#
#200000
0#
#205000
b0 !
b0 3
b11111111 "
b11111111 +
1#
#210000
0#
#215000
1#
#220000
0#
b1011010 $
b1011010 (
b111100 %
b111100 )
b111100 '
b111100 *
#225000
b1011010 ,
b111100 -
b111100 .
1#
#230000
0#
#235000
b1011010 /
b0 0
1#
#240000
0#
#245000
01
1#
#250000
0#
#255000
b0 "
b0 +
b1100100 !
b1100100 3
1#
