t625240/verilog_simulation/src/your_design.v
module pipelined_alu #(
    parameter WIDTH = 16
)(
    input  wire                  clk,
    input  wire                  rst,
    input  wire [WIDTH-1:0]      a,
    input  wire [WIDTH-1:0]      b,
    input  wire [3:0]            op,         // 4-bit opcode
    output reg  [WIDTH-1:0]      result,
    output reg                   overflow,
    output reg                   underflow,
    output reg                   invalid_op,
    output reg                   is_equal,
    output reg                   is_less
);

    reg [WIDTH:0] extended;  // For detecting overflow

    always @(posedge clk or posedge rst) begin
        if (rst) begin
            result     <= 0;
            overflow   <= 0;
            underflow  <= 0;
            invalid_op <= 0;
            is_equal   <= 0;
            is_less    <= 0;
        end else begin
            // Reset exception flags
            overflow   <= 0;
            underflow  <= 0;
            invalid_op <= 0;
            is_equal   <= 0;
            is_less    <= 0;

            case (op)
                4'b0000: begin // ADD
                    extended  = a + b;
                    result    <= extended[WIDTH-1:0];
                    overflow  <= extended[WIDTH];
                end
                4'b0001: begin // SUB
                    extended  = a - b;
                    result    <= extended[WIDTH-1:0];
                    underflow <= (a < b);
                end
                4'b0010: result <= a & b;         // AND
                4'b0011: result <= a | b;         // OR
                4'b0100: result <= a ^ b;         // XOR
                4'b0101: result <= ~a;            // NOT (on a)
                4'b0110: result <= a << 1;        // Shift Left
                4'b0111: result <= a >> 1;        // Shift Right
                4'b1000: is_equal <= (a == b);    // Compare Equal
                4'b1001: is_less  <= (a < b);     // Compare Less Than
                default: begin
                    result     <= 0;
                    invalid_op <= 1;
                end
            endcase
        end
    end

endmodule

t625240/verilog_simulation/src/testbench.v
module tb_pipelined_alu;

    parameter WIDTH = 16;

    reg  clk, rst;
    reg  [WIDTH-1:0] a, b;
    reg  [3:0] op;
    wire [WIDTH-1:0] result;
    wire overflow, underflow, invalid_op, is_equal, is_less;

    // DUT instance
    pipelined_alu #(.WIDTH(WIDTH)) dut (
        .clk(clk),
        .rst(rst),
        .a(a),
        .b(b),
        .op(op),
        .result(result),
        .overflow(overflow),
        .underflow(underflow),
        .invalid_op(invalid_op),
        .is_equal(is_equal),
        .is_less(is_less)
    );

    // Clock generation
    always #5 clk = ~clk;

    initial begin
        $dumpfile("output/tb_pipelined_alu.vcd");
        $dumpvars(0, tb_pipelined_alu);

        // Initialize
        clk = 0;
        rst = 1;
        a = 0;
        b = 0;
        op = 0;
        #10;

        rst = 0;

        // ADD
        a = 100; b = 200; op = 4'b0000;
        #10 $display("ADD: %0d + %0d = %0d, Overflow: %b", a, b, result, overflow);

        // SUB
        a = 50; b = 80; op = 4'b0001;
        #10 $display("SUB: %0d - %0d = %0d, Underflow: %b", a, b, result, underflow);

        // AND
        a = 16'hFF00; b = 16'h0F0F; op = 4'b0010;
        #10 $display("AND: %h & %h = %h", a, b, result);

        // OR
        a = 16'hA5A5; b = 16'h5A5A; op = 4'b0011;
        #10 $display("OR : %h | %h = %h", a, b, result);

        // XOR
        a = 16'hAAAA; b = 16'hFFFF; op = 4'b0100;
        #10 $display("XOR: %h ^ %h = %h", a, b, result);

        // NOT
        a = 16'hF0F0; op = 4'b0101;
        #10 $display("NOT: ~%h = %h", a, result);

        // Shift Left
        a = 16'h0001; op = 4'b0110;
        #10 $display("SHL: %h << 1 = %h", a, result);

        // Shift Right
        a = 16'h8000; op = 4'b0111;
        #10 $display("SHR: %h >> 1 = %h", a, result);

        // Compare Equal
        a = 1234; b = 1234; op = 4'b1000;
        #10 $display("CMP EQ: %0d == %0d? %b", a, b, is_equal);

        // Compare Less Than
        a = 10; b = 50; op = 4'b1001;
        #10 $display("CMP LT: %0d < %0d? %b", a, b, is_less);

        // Invalid Op
        op = 4'b1111;
        #10 $display("Invalid Op Test: Invalid Flag = %b", invalid_op);

        $finish;
    end

endmodule

t625240/verilog_simulation/output/tb_pipelined_alu.vcd
$date
	Tue Apr  1 09:33:57 2025
$end
$version
	Icarus Verilog
$end
$timescale
	1s
$end
$scope module tb_pipelined_alu $end
$var wire 1 ! underflow $end
$var wire 16 " result [15:0] $end
$var wire 1 # overflow $end
$var wire 1 $ is_less $end
$var wire 1 % is_equal $end
$var wire 1 & invalid_op $end
$var parameter 32 ' WIDTH $end
$var reg 16 ( a [15:0] $end
$var reg 16 ) b [15:0] $end
$var reg 1 * clk $end
$var reg 4 + op [3:0] $end
$var reg 1 , rst $end
$scope module dut $end
$var wire 16 - a [15:0] $end
$var wire 16 . b [15:0] $end
$var wire 1 * clk $end
$var wire 4 / op [3:0] $end
$var wire 1 , rst $end
$var parameter 32 0 WIDTH $end
$var reg 17 1 extended [16:0] $end
$var reg 1 & invalid_op $end
$var reg 1 % is_equal $end
$var reg 1 $ is_less $end
$var reg 1 # overflow $end
$var reg 16 2 result [15:0] $end
$var reg 1 ! underflow $end
$upscope $end
$upscope $end
$enddefinitions $end
$comment Show the parameter values. $end
$dumpall
b10000 0
b10000 '
$end
#0
$dumpvars
b0 2
bx 1
b0 /
b0 .
b0 -
1,
b0 +
0*
b0 )
b0 (
0&
0%
0$
0#
b0 "
0!
$end
#5
1*
#10
0*
b11001000 )
b11001000 .
b1100100 (
b1100100 -
0,
#15
b100101100 "
b100101100 2
b100101100 1
1*
#20
0*
b1 +
b1 /
b1010000 )
b1010000 .
b110010 (
b110010 -
#25
1!
b1111111111100010 "
b1111111111100010 2
b11111111111100010 1
1*
#30
0*
b10 +
b10 /
b111100001111 )
b111100001111 .
b1111111100000000 (
b1111111100000000 -
#35
b111100000000 "
b111100000000 2
0!
1*
#40
0*
b11 +
b11 /
b101101001011010 )
b101101001011010 .
b1010010110100101 (
b1010010110100101 -
#45
b1111111111111111 "
b1111111111111111 2
1*
#50
0*
b100 +
b100 /
b1111111111111111 )
b1111111111111111 .
b1010101010101010 (
b1010101010101010 -
#55
b101010101010101 "
b101010101010101 2
1*
#60
0*
b101 +
b101 /
b1111000011110000 (
b1111000011110000 -
#65
b111100001111 "
b111100001111 2
1*
#70
0*
b110 +
b110 /
b1 (
b1 -
#75
b10 "
b10 2
1*
#80
0*
b111 +
b111 /
b1000000000000000 (
b1000000000000000 -
#85
b100000000000000 "
b100000000000000 2
1*
#90
0*
b1000 +
b1000 /
b10011010010 )
b10011010010 .
b10011010010 (
b10011010010 -
#95
1%
1*
#100
0*
b1001 +
b1001 /
b110010 )
b110010 .
b1010 (
b1010 -
#105
1$
0%
1*
#110
0*
b1111 +
b1111 /
#115
1&
b0 "
b0 2
0$
1*
