t625028/verilog_simulation/src/your_design.v
module two_stage_sync (
    input  wire clk_a,
    input  wire rst_a,
    input  wire signal_a,
    input  wire clk_b,
    input  wire rst_b,
    output reg  signal_b
);

    reg signal_a_ff;
    reg sync_1, sync_2;

    // Sending domain (clk_a)
    always @(posedge clk_a or posedge rst_a) begin
        if (rst_a)
            signal_a_ff <= 0;
        else
            signal_a_ff <= signal_a;
    end

    // Receiving domain (clk_b) with two-stage flip-flop synchronization
    always @(posedge clk_b or posedge rst_b) begin
        if (rst_b) begin
            sync_1 <= 0;
            sync_2 <= 0;
            signal_b <= 0;
        end else begin
            sync_1 <= signal_a_ff;  // First stage
            sync_2 <= sync_1;       // Second stage
            signal_b <= sync_2;
        end
    end

endmodule

d02042025/t625028/verilog_simulation/src/testbench.v

`timescale 1ns/1ps

module two_stage_sync_tb;
    
    reg clk_a, rst_a, signal_a;
    reg clk_b, rst_b;
    wire signal_b;
    
    // Instantiate the DUT (Device Under Test)
    two_stage_sync dut (
        .clk_a(clk_a),
        .rst_a(rst_a),
        .signal_a(signal_a),
        .clk_b(clk_b),
        .rst_b(rst_b),
        .signal_b(signal_b)
    );
    
    // Clock generation
    always #5  clk_a = ~clk_a; // 10 ns period
    always #7  clk_b = ~clk_b; // 14 ns period (asynchronous to clk_a)
    initial begin
        $dumpfile("output/two_stage_sync_tb.vcd");
        $dumpvars(0, two_stage_sync_tb);
    end

    initial begin
        // Initialize signals
        clk_a = 0; clk_b = 0;
        rst_a = 1; rst_b = 1;
        signal_a = 0;
        
        // Apply reset
        #20 rst_a = 0;
        #20 rst_b = 0;
        
        // Apply test stimulus
        #30 signal_a = 1;  // Set signal_a high
        #20 signal_a = 0;  // Set signal_a low
        #40 signal_a = 1;  // Set signal_a high again
        #20 signal_a = 0;  // Set signal_a low again
        
        // Finish simulation
        #100 $finish;
    end
    
    // Monitor outputs
    initial begin
        $monitor("%t: signal_a=%b, signal_b=%b", $time, signal_a, signal_b);
    end
    
endmodule

t625028/verilog_simulation/output/two_stage_sync_tb.vcd
$date
	Wed Apr  2 09:39:43 2025
$end
$version
	Icarus Verilog
$end
$timescale
	1ps
$end
$scope module two_stage_sync_tb $end
$var wire 1 ! signal_b $end
$var reg 1 " clk_a $end
$var reg 1 # clk_b $end
$var reg 1 $ rst_a $end
$var reg 1 % rst_b $end
$var reg 1 & signal_a $end
$scope module dut $end
$var wire 1 " clk_a $end
$var wire 1 # clk_b $end
$var wire 1 $ rst_a $end
$var wire 1 % rst_b $end
$var wire 1 & signal_a $end
$var reg 1 ' signal_a_ff $end
$var reg 1 ! signal_b $end
$var reg 1 ( sync_1 $end
$var reg 1 ) sync_2 $end
$upscope $end
$upscope $end
$enddefinitions $end
$comment Show the parameter values. $end
$dumpall
$end
#0
$dumpvars
0)
0(
0'
0&
1%
1$
0#
0"
0!
$end
#5000
1"
#7000
1#
#10000
0"
#14000
0#
#15000
1"
#20000
0"
0$
#21000
1#
#25000
1"
#28000
0#
#30000
0"
#35000
1"
1#
#40000
0"
0%
#42000
0#
#45000
1"
#49000
1#
#50000
0"
#55000
1"
#56000
0#
#60000
0"
#63000
1#
#65000
1"
#70000
0"
0#
1&
#75000
1'
1"
#77000
1(
1#
#80000
0"
#84000
0#
#85000
1"
#90000
0"
0&
#91000
1)
1#
#95000
0'
1"
#98000
0#
#100000
0"
#105000
1!
0(
1"
1#
#110000
0"
#112000
0#
#115000
1"
#119000
0)
1#
#120000
0"
#125000
1"
#126000
0#
#130000
0"
1&
#133000
0!
1#
#135000
1'
1"
#140000
0"
0#
#145000
1"
#147000
1(
1#
#150000
0"
0&
#154000
0#
#155000
0'
1"
#160000
0"
#161000
1)
0(
1#
#165000
1"
#168000
0#
#170000
0"
#175000
1!
0)
1"
1#
#180000
0"
#182000
0#
#185000
1"
#189000
0!
1#
