t625087/src/your_design.v
module CachePrefetch #(parameter CACHE_SIZE = 16, BLOCK_SIZE = 4, ADDR_WIDTH = 8)(
    input clk, reset, read_enable,
    input [ADDR_WIDTH-1:0] addr,
    output reg hit,
    output reg [31:0] data_out
);
    reg [31:0] cache_mem [CACHE_SIZE-1:0];
    reg [ADDR_WIDTH-1:0] tag_array [CACHE_SIZE-1:0];
    reg valid [CACHE_SIZE-1:0];
    reg [ADDR_WIDTH-1:0] prefetch_addr;
    integer index,i, prefetch_index;
    always @(posedge clk or posedge reset) begin
        if (reset) begin
            //integer i;
            for (i = 0; i < CACHE_SIZE; i = i + 1) valid[i] <= 0;
            hit <= 0;
        end 
        else if (read_enable) begin
            index = addr % CACHE_SIZE;
            if (valid[index] && tag_array[index] == addr) begin
                hit <= 1;
                data_out <= cache_mem[index];
            end else begin
                hit <= 0;
                #5 cache_mem[index] <= {addr, addr}; // Fake Data
                tag_array[index] <= addr;
                valid[index] <= 1;

                // Prefetch Next Block
                prefetch_addr = addr + BLOCK_SIZE;
                prefetch_index = prefetch_addr % CACHE_SIZE;
                cache_mem[prefetch_index] <= {prefetch_addr, prefetch_addr}; 
                tag_array[prefetch_index] <= prefetch_addr;
                valid[prefetch_index] <= 1;
            end
        end
    end
endmodule

t625087/src/testbench.v
`timescale 1ns / 1ps

module tb_CachePrefetch();
    parameter CACHE_SIZE = 16;
    parameter BLOCK_SIZE = 4;
    parameter ADDR_WIDTH = 8;

    reg clk, reset, read_enable;
    reg [ADDR_WIDTH-1:0] addr;
    wire hit;
    wire [31:0] data_out;
    integer i,j;
    // Instantiate the DUT
    CachePrefetch #(
        .CACHE_SIZE(CACHE_SIZE),
        .BLOCK_SIZE(BLOCK_SIZE),
        .ADDR_WIDTH(ADDR_WIDTH)
    ) dut (
        .clk(clk),
        .reset(reset),
        .read_enable(read_enable),
        .addr(addr),
        .hit(hit),
        .data_out(data_out)
    );

    // Clock generation (100 MHz)
    initial begin
        clk = 0;
        forever #5 clk = ~clk;
    end
initial begin
        $dumpfile("output/ tb_CachePrefetch.vcd");
        $dumpvars(0,  tb_CachePrefetch);
    end


    // Test sequence
    initial begin
        // Initialize signals
        reset = 1;
        read_enable = 0;
        addr = 0;
        #20;

        // Release reset
        reset = 0;
        #10;

        // Test 1: Cache miss followed by prefetch
        $display("Test 1: Cache miss and prefetch");
        read_enable = 1;
        addr = 8'h10;
        #10;
        if (hit === 0) $display("PASS: Cache miss for addr=0x%0h", addr);
        else $display("FAIL: Expected miss for addr=0x%0h", addr);
        #10;

        // Test 2: Cache hit (same address)
        $display("Test 2: Cache hit (same address)");
        addr = 8'h10;
        #10;
        if (hit === 1) $display("PASS: Cache hit for addr=0x%0h", addr);
        else $display("FAIL: Expected hit for addr=0x%0h", addr);
        #10;

        // Test 3: Verify prefetched block (addr + BLOCK_SIZE)
        $display("Test 3: Prefetch verification");
        addr = 8'h14; // 0x10 + BLOCK_SIZE (4)
        #10;
        if (hit === 1) $display("PASS: Prefetch hit for addr=0x%0h", addr);
        else $display("FAIL: Prefetch miss for addr=0x%0h", addr);
        #10;

        // Test 4: Random address test
        $display("Test 4: Random address test");
        for (i = 0; i < 5; i++) begin
            addr = $urandom_range(0, 255); // Random 8-bit address
            #10;
            if (hit === 0) $display("PASS: Miss for random addr=0x%0h", addr);
            else $display("FAIL: Unexpected hit for addr=0x%0h", addr);
            #10;
        end

        // Test 5: Reset behavior
        $display("Test 5: Reset test");
        reset = 1;
        #10;
        if (hit === 0) $display("PASS: Cache invalidated after reset");
        else $display("FAIL: Reset did not invalidate cache");
        #10;

        $display("All tests completed.");
        $finish;
    end

    // Monitor for debug
    always @(posedge clk) begin
        $display("Time=%0t: addr=0x%0h, hit=%b, data_out=0x%0h",
            $time, addr, hit, data_out);
    end
endmodule

t625087/output/ tb_CachePrefetch.vcd
$date
	Tue Apr  1 10:59:52 2025
$end
$version
	Icarus Verilog
$end
$timescale
	1ps
$end
$scope module tb_CachePrefetch $end
$var wire 1 ! hit $end
$var wire 32 " data_out [31:0] $end
$var parameter 32 # ADDR_WIDTH $end
$var parameter 32 $ BLOCK_SIZE $end
$var parameter 32 % CACHE_SIZE $end
$var reg 8 & addr [7:0] $end
$var reg 1 ' clk $end
$var reg 1 ( read_enable $end
$var reg 1 ) reset $end
$var integer 32 * i [31:0] $end
$scope module dut $end
$var wire 8 + addr [7:0] $end
$var wire 1 ' clk $end
$var wire 1 ( read_enable $end
$var wire 1 ) reset $end
$var parameter 32 , ADDR_WIDTH $end
$var parameter 32 - BLOCK_SIZE $end
$var parameter 32 . CACHE_SIZE $end
$var reg 32 / data_out [31:0] $end
$var reg 1 ! hit $end
$var reg 8 0 prefetch_addr [7:0] $end
$var integer 32 1 i [31:0] $end
$var integer 32 2 index [31:0] $end
$var integer 32 3 prefetch_index [31:0] $end
$upscope $end
$upscope $end
$enddefinitions $end
$comment Show the parameter values. $end
$dumpall
b10000 .
b100 -
b1000 ,
b10000 %
b100 $
b1000 #
$end
#0
$dumpvars
bx 3
bx 2
b10000 1
bx 0
bx /
b0 +
bx *
1)
0(
0'
b0 &
bx "
0!
$end
#5000
b10000 1
1'
#10000
0'
#15000
b10000 1
1'
#20000
0'
0)
#25000
1'
#30000
0'
b10000 &
b10000 +
1(
#35000
b0 2
1'
#40000
b100 3
b10100 0
0'
#45000
b1000000010000 "
b1000000010000 /
1!
1'
#50000
0'
#55000
1'
#60000
0'
#65000
1'
#70000
0'
b10100 &
b10100 +
#75000
b1010000010100 "
b1010000010100 /
b100 2
1'
#80000
0'
#85000
1'
#90000
0'
b10010010 &
b10010010 +
b0 *
#95000
0!
b10 2
1'
#100000
b110 3
b10010110 0
0'
#105000
b1001001010010010 "
b1001001010010010 /
1!
1'
#110000
0'
b1000000 &
b1000000 +
b1 *
#115000
0!
b0 2
1'
#120000
b100 3
b1000100 0
0'
#125000
b100000001000000 "
b100000001000000 /
1!
1'
#130000
0'
b100 &
b100 +
b10 *
#135000
0!
b100 2
1'
#140000
b1000 3
b1000 0
0'
#145000
b10000000100 "
b10000000100 /
1!
1'
#150000
0'
b110001 &
b110001 +
b11 *
#155000
0!
b1 2
1'
#160000
b101 3
b110101 0
0'
#165000
b11000100110001 "
b11000100110001 /
1!
1'
#170000
0'
b10000110 &
b10000110 +
b100 *
#175000
0!
b110 2
1'
#180000
b1010 3
b10001010 0
0'
#185000
b1000011010000110 "
b1000011010000110 /
1!
1'
#190000
0!
b10000 1
0'
1)
b101 *
#195000
b10000 1
1'
#200000
0'
#205000
b10000 1
1'
